unofficial_twitter_client/__init__.py
unofficial_twitter_client/android.py
unofficial_twitter_client/config.py
unofficial_twitter_client/oauth.py
unofficial_twitter_client/web.py
unofficial_twitter_client-0.2.0.dist-info/LICENSE
unofficial_twitter_client-0.2.0.dist-info/METADATA
unofficial_twitter_client-0.2.0.dist-info/WHEEL
unofficial_twitter_client-0.2.0.dist-info/top_level.txt
unofficial_twitter_client-0.2.0.dist-info/RECORD
