Metadata-Version: 2.1
Name: unofficial-twitter-client
Version: 0.2.0
Summary: Unofficial Twitter Client API
Home-page: https://github.com/abshrimp/unofficial_twitter_client
Author: abshrimp
Author-email: abshrimps@gmail.com
License: UNKNOWN
Platform: UNKNOWN
Classifier: Programming Language :: Python :: 3
Classifier: License :: OSI Approved :: MIT License
Classifier: Operating System :: OS Independent
Classifier: Development Status :: 3 - Alpha
Classifier: Intended Audience :: Developers
Classifier: Topic :: Software Development :: Libraries :: Python Modules
Requires-Python: >=3.7
License-File: LICENSE
Requires-Dist: requests-oauthlib>=1.3.1
Requires-Dist: requests>=2.31.0
